Processor_JK_8BIT.srcs/sources_1/new/ALU_8BIT.v
`timescale 1ns / 1ps
//////////////////////////////////////////////////////////////////////////////////
// Company: 
// Engineer: Jaikrishnan P
// 
// Create Date: 08.02.2026 17:18:55
// Design Name: 
// Module Name: ALU_8BIT
// Project Name: Processor_JK
// Target Devices: 
// Tool Versions: 
// Description: 
// 
// Dependencies: 
// 
// Revision:
// Revision 0.01 - File Created
// Additional Comments:
// 
//////////////////////////////////////////////////////////////////////////////////
module adder8bit (
    input [7:0] A, B,
    output [8:0] Sum_Out // 9th bit is the Carry
);
    assign Sum_Out = A + B;
endmodule

module subtractor8bit (
    input [7:0] A, B,
    output [8:0] Diff_Out // 9th bit is Borrow/Sign info
);
    assign Diff_Out = A - B;
endmodule

module multiplier8bit (
    input [7:0] A, B,
    output [15:0] Prod_Out // Full 16-bit result
);
    assign Prod_Out = A * B;
endmodule

module divider8bit (
    input [7:0] A, B,
    output [7:0] Quotient,
    output [7:0] Remainder,
    output Div_Err
);
    // If B is 0, set Error high, otherwise do the math
    assign Div_Err = (B == 0); 
    assign Quotient = (B == 0) ? 8'b0 : (A / B);
    assign Remainder = (B == 0) ? 8'b0 : (A % B);
endmodule

module ALU_8BIT(
    input [7:0] A, B,
    input [3:0] ALU_Op,   // Matches your ISA Opcode (4 bits)
    output reg [7:0] Result,
    output reg [7:0] Result_High, // For Mul/Div upper bits
    output reg Z, N, C, V, Err    // Flags: Zero, Neg, Carry, Overflow, Error
);

    // --- Wires for internal connections ---
    wire [8:0] add_res, sub_res;
    wire [15:0] mul_res;
    wire [7:0] div_quot, div_rem;
    wire div_err_sig;

    // --- Instantiate the Workers ---
    adder8bit      u_add (.A(A), .B(B), .Sum_Out(add_res));
    subtractor8bit u_sub (.A(A), .B(B), .Diff_Out(sub_res));
    multiplier8bit u_mul (.A(A), .B(B), .Prod_Out(mul_res));
    divider8bit    u_div (.A(A), .B(B), .Quotient(div_quot), .Remainder(div_rem), .Div_Err(div_err_sig));

    // --- Main Logic ---
    always @(*) begin
        // 1. Reset defaults
        Result = 0; Result_High = 0;
        Z = 0; N = 0; C = 0; V = 0; Err = 0;

        case(ALU_Op)
            // --- ARITHMETIC ---
            4'b0000: begin // ADD
                Result = add_res[7:0];
                C = add_res[8];
                // Overflow: (Pos+Pos=Neg) or (Neg+Neg=Pos)
                V = (A[7] & B[7] & ~Result[7]) | (~A[7] & ~B[7] & Result[7]);
            end

            4'b0001: begin // SUB
                Result = sub_res[7:0];
                C = sub_res[8]; 
                // Overflow: (Pos-Neg=Neg) or (Neg-Pos=Pos)
                V = (A[7] & ~B[7] & ~Result[7]) | (~A[7] & B[7] & Result[7]);
            end

            4'b0010: begin // MUL
                Result = mul_res[7:0];       // Lower 8 bits
                Result_High = mul_res[15:8]; // Upper 8 bits
                V = (Result_High != 0);      // Overflow if result > 255
            end

            4'b0011: begin // DIV
                Result = div_quot;
                Result_High = div_rem;
                Err = div_err_sig;
            end

            // --- LOGIC ---
            4'b0100: Result = A & B; // AND
            4'b0101: Result = A | B; // OR
            4'b0110: Result = A ^ B; // XOR

            // --- MOVES & SPECIALS ---
            4'b0111: Result = A; // MOV (Pass A through)
            
            4'b1000: Result = B; // LDI (Pass B/Immediate through)
            
            4'b1011: begin // CMP (Compare) -> Same as SUB, but we ignore Result later
                Result = sub_res[7:0]; 
                C = sub_res[8];
                V = (A[7] & ~B[7] & ~Result[7]) | (~A[7] & B[7] & Result[7]);
            end

            default: Result = 8'b0; // Default safety
        endcase

        // 2. Universal Flags (Apply to all ops)
        Z = (Result == 0 && Result_High == 0); // Zero flag
        N = Result[7]; // Negative flag (MSB)
    end
endmodule

Processor_JK_8BIT.srcs/sim_1/new/tb_alu.v
`timescale 1ns / 1ps
//////////////////////////////////////////////////////////////////////////////////
// Company: 
// Engineer: Jaikrishnan P
// 
// Create Date: 08.02.2026 19:34:46
// Design Name: ALU_8BIT
// Module Name: tb_alu
// Project Name: Processor_JK
// Target Devices: 
// Tool Versions: 
// Description: 
// 
// Dependencies: 
// 
// Revision:
// Revision 0.01 - File Created
// Additional Comments:
// 
//////////////////////////////////////////////////////////////////////////////////




module tb_alu;

    // 1. Declare Inputs as Reg (Because we set the values)
    reg [7:0] A, B;
    reg [3:0] ALU_Op;

    // 2. Declare Outputs as Wire (Because we just watch them)
    wire [7:0] Result;
    wire [7:0] Result_High;
    wire Z, N, C, V, Err;

    // 3. Instantiate the Unit Under Test (UUT)
    // Make sure the name 'ALU_8BIT' matches your design file exactly!
    ALU_8BIT uut (
        .A(A), 
        .B(B), 
        .ALU_Op(ALU_Op), 
        .Result(Result), 
        .Result_High(Result_High), 
        .Z(Z), .N(N), .C(C), .V(V), .Err(Err)
    );

    // 4. Test Procedure
    initial begin
        // Setup for Waveform Viewer (GTKWave / Vivado)
        $dumpfile("alu_simulation.vcd"); // The file to open in GTKWave
        $dumpvars(0, tb_alu);

        // Header for the Console Output
        $display("------------------------------------------------------------------");
        $display("   ALU TESTBENCH START - CHECKING ALL OPS                         ");
        $display("------------------------------------------------------------------");
        $display(" Time | Opcode |  A  |  B  | Result | Res_Hi | Z N C V E | Operation");
        $display("------+--------+-----+-----+--------+--------+-----------+----------");

        // --- TEST 1: ADDITION (10 + 20 = 30) ---
        A = 10; B = 20; ALU_Op = 4'b0000; #10;
        print_result("ADD (Normal)");

        // --- TEST 2: ADDITION OVERFLOW (127 + 1 = -128 in signed) ---
        // 127 (01111111) + 1 = 128 (10000000). The sign bit flips! V should be 1.
        A = 8'd127; B = 8'd1; ALU_Op = 4'b0000; #10;
        print_result("ADD (Overflow Check)");

        // --- TEST 3: SUBTRACTION (50 - 20 = 30) ---
        A = 50; B = 20; ALU_Op = 4'b0001; #10;
        print_result("SUB (Normal)");

        // --- TEST 4: MULTIPLICATION (10 * 10 = 100) ---
        A = 10; B = 10; ALU_Op = 4'b0010; #10;
        print_result("MUL (Normal)");

        // --- TEST 5: MULTIPLICATION BIG (100 * 10 = 1000) ---
        // 1000 is too big for 8 bits. It needs Result_High.
        // 1000 = 0x03E8. So Result=E8 (232), Result_High=03 (3).
        A = 100; B = 10; ALU_Op = 4'b0010; #10;
        print_result("MUL (High Byte Check)");

        // --- TEST 6: DIVISION (100 / 2 = 50) ---
        A = 100; B = 2; ALU_Op = 4'b0011; #10;
        print_result("DIV (Normal)");

        // --- TEST 7: DIVISION BY ZERO (CRITICAL!) ---
        // Should trigger the 'Err' flag.
        A = 50; B = 0; ALU_Op = 4'b0011; #10;
        print_result("DIV (Zero Error Check)");

        // --- TEST 8: LOGIC AND (11110000 & 10101010) ---
        A = 8'hF0; B = 8'hAA; ALU_Op = 4'b0100; #10;
        print_result("AND Logic");

        // --- TEST 9: COMPARE (CMP 10, 10) ---
        // 10 - 10 = 0. Should set Zero Flag (Z=1).
        A = 10; B = 10; ALU_Op = 4'b1011; #10;
        print_result("CMP (Equal Check)");

        // --- TEST 10: COMPARE (CMP 10, 20) ---
        // 10 - 20 = -10. Should set Negative Flag (N=1).
        A = 10; B = 20; ALU_Op = 4'b1011; #10;
        print_result("CMP (Less Than Check)");

        $display("------------------------------------------------------------------");
        $display("           TEST COMPLETE                                     ");
        $display("------------------------------------------------------------------");
        $finish;
    end

    // Helper Task to print readable output automatically
    task print_result(input [30*8:1] op_name);
        begin
            $display(" %4t |  %b  | %3d | %3d |   %3d  |   %3d  | %b %b %b %b %b | %s", 
                $time, ALU_Op, A, B, Result, Result_High, Z, N, C, V, Err, op_name);
        end
    endtask

endmodule

Processor_JK_8BIT.sim/sim_1/behav/xsim/alu_simulation.vcd
$date
   Sun Feb  8 19:37:05 2026
$end

$version
  2025.2
  $dumpfile ("alu_simulation.vcd") 
$end

$timescale
  1ps
$end

$scope module tb_alu $end
$var reg 8 ! A [7:0] $end
$var reg 8 " B [7:0] $end
$var reg 4 # ALU_Op [3:0] $end
$var wire 8 $ Result [7:0] $end
$var wire 8 % Result_High [7:0] $end
$var wire 1 & Z $end
$var wire 1 ' N $end
$var wire 1 ( C $end
$var wire 1 ) V $end
$var wire 1 * Err $end
$scope module uut $end
$var wire 8 + A [7:0] $end
$var wire 8 , B [7:0] $end
$var wire 4 - ALU_Op [3:0] $end
$var reg 8 . Result [7:0] $end
$var reg 8 / Result_High [7:0] $end
$var reg 1 0 Z $end
$var reg 1 1 N $end
$var reg 1 2 C $end
$var reg 1 3 V $end
$var reg 1 4 Err $end
$var wire 9 5 add_res [8:0] $end
$var wire 9 6 sub_res [8:0] $end
$var wire 16 7 mul_res [15:0] $end
$var wire 8 8 div_quot [7:0] $end
$var wire 8 9 div_rem [7:0] $end
$var wire 1 : div_err_sig $end
$scope module u_add $end
$var wire 8 + A [7:0] $end
$var wire 8 , B [7:0] $end
$var wire 9 5 Sum_Out [8:0] $end
$upscope $end
$scope module u_sub $end
$var wire 8 + A [7:0] $end
$var wire 8 , B [7:0] $end
$var wire 9 6 Diff_Out [8:0] $end
$upscope $end
$scope module u_mul $end
$var wire 8 + A [7:0] $end
$var wire 8 , B [7:0] $end
$var wire 16 7 Prod_Out [15:0] $end
$upscope $end
$scope module u_div $end
$var wire 8 + A [7:0] $end
$var wire 8 , B [7:0] $end
$var wire 8 8 Quotient [7:0] $end
$var wire 8 9 Remainder [7:0] $end
$var wire 1 : Div_Err $end
$upscope $end
$upscope $end
$scope task print_result $end
$var reg 240 ; op_name [239:0] $end
$upscope $end
$upscope $end
$enddefinitions $end

#0
$dumpvars
b1010 !
b10100 "
b0 #
b11110 $
b0 %
0&
0'
0(
0)
0*
b1010 +
b10100 ,
b0 -
b11110 .
b0 /
00
01
02
03
04
b11110 5
b111110110 6
b11001000 7
b0 8
b1010 9
0:
bx ;
$end

#10000
b1111111 !
b1 "
b10000000 $
1'
1)
b1111111 +
b1 ,
b10000000 .
11
13
b10000000 5
b1111110 6
b1111111 7
b1111111 8
b0 9
b10000010100010001000100001000000010100001001110011011110111001001101101011000010110110000101001 ;

#20000
b110010 !
b10100 "
b1 #
b11110 $
0'
0)
b110010 +
b10100 ,
b1 -
b11110 .
01
03
b1000110 5
b11110 6
b1111101000 7
b10 8
b1010 9
b100000101000100010001000010000000101000010011110111011001100101011100100110011001101100011011110111011100100000010000110110100001100101011000110110101100101001 ;

#30000
b1010 !
b1010 "
b10 #
b1100100 $
b1010 +
b1010 ,
b10 -
b1100100 .
b10100 5
b0 6
b1100100 7
b1 8
b0 9
b10100110101010101000010001000000010100001001110011011110111001001101101011000010110110000101001 ;

#40000
b1100100 !
b11101000 $
b11 %
1'
1)
b1100100 +
b11101000 .
b11 /
11
13
b1101110 5
b1011010 6
b1111101000 7
b1010 8
b10011010101010101001100001000000010100001001110011011110111001001101101011000010110110000101001 ;

#50000
b10 "
b11 #
b110010 $
b0 %
0'
0)
b10 ,
b11 -
b110010 .
b0 /
01
03
b1100110 5
b1100010 6
b11001000 7
b110010 8
b10011010101010101001100001000000010100001001000011010010110011101101000001000000100001001111001011101000110010100100000010000110110100001100101011000110110101100101001 ;

#60000
b110010 !
b0 "
b0 $
1&
1*
b110010 +
b0 ,
b0 .
10
14
b110010 5
b110010 6
b0 7
b0 8
1:
b10001000100100101010110001000000010100001001110011011110111001001101101011000010110110000101001 ;

#70000
b11110000 !
b10101010 "
b100 #
b10100000 $
0&
1'
0*
b11110000 +
b10101010 ,
b100 -
b10100000 .
00
11
04
b110011010 5
b1000110 6
b1001111101100000 7
b1 8
b1000110 9
0:
b1000100010010010101011000100000001010000101101001100101011100100110111100100000010001010111001001110010011011110111001000100000010000110110100001100101011000110110101100101001 ;

#80000
b1010 !
b1010 "
b1011 #
b0 $
1&
0'
b1010 +
b1010 ,
b1011 -
b0 .
10
01
b10100 5
b0 6
b1100100 7
b0 9
b10000010100111001000100001000000100110001101111011001110110100101100011 ;

#90000
b10100 "
b11110110 $
0&
1'
1(
b10100 ,
b11110110 .
00
11
12
b11110 5
b111110110 6
b11001000 7
b0 8
b1010 9
b100001101001101010100000010000000101000010001010111000101110101011000010110110000100000010000110110100001100101011000110110101100101001 ;

#100000
b10000110100110101010000001000000010100001001100011001010111001101110011001000000101010001101000011000010110111000100000010000110110100001100101011000110110101100101001 ;
